wqet_grader/__init__.py
wqet_grader/grading.py
wqet_grader/server.py
wqet_grader/transport.py
wqet_grader/utils.py
wqet_grader/routes/__init__.py
wqet_grader/routes/grade.py
wqet_grader/routes/info.py
wqet_grader-0.2.2.dist-info/METADATA
wqet_grader-0.2.2.dist-info/WHEEL
wqet_grader-0.2.2.dist-info/top_level.txt
wqet_grader-0.2.2.dist-info/RECORD
