Metadata-Version: 2.1
Name: wqet_grader
Version: 0.2.2
Summary: Grading for WQET
Home-page: https://github.com/worldquant/wqet-grader
Requires-Dist: pandas >=1.3.3
Requires-Dist: requests >=2.26.0
Requires-Dist: category-encoders >=2.2.2
Requires-Dist: scikit-learn >=1.0
Requires-Dist: matplotlib >=3.7
